Workbook

Sheet iOS Camera (Built-in)
A1: LOG PENGUJIAN: IOS CAMERA (BUILT-IN)
A2: No | B2: Waktu | C2: URL | D2: Label Aktual | E2: Kategori | F2: Hasil Scanner | G2: TP | H2: FP | I2: FN | J2: TN | K2: Benar? | L2: Catatan
A3: =ROW()-2 -> 1 | B3: 2026-04-06 16:39:23 | C3: https://composerprogrammer.com/introductiontocomputermusic.pdf | D3: safe | E3: Live Safe (Tech News) | F3: Aman | G3: 0 | H3: 0 | I3: 0 | J3: 1 | K3: ✅
A4: =ROW()-2 -> 2 | B4: 2026-04-06 16:39:23 | C4: https://jaso1024.com/mvidia/ | D4: safe | E4: Live Safe (Tech News) | F4: Aman | G4: 0 | H4: 0 | I4: 0 | J4: 1 | K4: ✅
A5: =ROW()-2 -> 3 | B5: 2026-04-06 16:39:23 | C5: https://github.com/siddharthvaddem/openscreen | D5: safe | E5: Live Safe (Tech News) | F5: Aman | G5: 0 | H5: 0 | I5: 0 | J5: 1 | K5: ✅
A6: =ROW()-2 -> 4 | B6: 2026-04-06 16:39:23 | C6: https://taggart-tech.com/reckoning/ | D6: safe | E6: Live Safe (Tech News) | F6: Aman | G6: 0 | H6: 0 | I6: 0 | J6: 1 | K6: ✅
A7: =ROW()-2 -> 5 | B7: 2026-04-06 16:39:24 | C7: https://jonno.nz/posts/what-if-your-browser-built-the-ui-for-you/ | D7: safe | E7: Live Safe (Tech News) | F7: Aman | G7: 0 | H7: 0 | I7: 0 | J7: 1 | K7: ✅
A8: =ROW()-2 -> 6 | B8: 2026-04-06 16:39:24 | C8: https://gist.github.com/karpathy/442a6bf555914893e9891c11519de94f | D8: safe | E8: Live Safe (Tech News) | F8: Aman | G8: 0 | H8: 0 | I8: 0 | J8: 1 | K8: ✅
A9: =ROW()-2 -> 7 | B9: 2026-04-06 16:39:24 | C9: https://twitter.com/VladTheInflator/status/2039577001531768906 | D9: safe | E9: Live Safe (Tech News) | F9: Aman | G9: 0 | H9: 0 | I9: 0 | J9: 1 | K9: ✅
A10: =ROW()-2 -> 8 | B10: 2026-04-06 16:39:24 | C10: https://blog.djhaskin.com/blog/writing-lisp-is-ai-resistant-and-im-sad/ | D10: safe | E10: Live Safe (Tech News) | F10: Aman | G10: 0 | H10: 0 | I10: 0 | J10: 1 | K10: ✅
A11: =ROW()-2 -> 9 | B11: 2026-04-06 16:39:24 | C11: https://teybannerman.com/strategy/2026/03/31/how-many-microsoft-copilot-are-there.html | D11: safe | E11: Live Safe (Tech News) | F11: Aman | G11: 0 | H11: 0 | I11: 0 | J11: 1 | K11: ✅
A12: =ROW()-2 -> 10 | B12: 2026-04-06 16:39:25 | C12: https://www.phoronix.com/news/Linux-7.0-AWS-PostgreSQL-Drop | D12: safe | E12: Live Safe (Tech News) | F12: Aman | G12: 0 | H12: 0 | I12: 0 | J12: 1 | K12: ✅
A13: =ROW()-2 -> 11 | B13: 2026-04-06 16:39:25 | C13: https://www.science.org/doi/10.1126/sciadv.aef5697 | D13: safe | E13: Live Safe (Tech News) | F13: Aman | G13: 0 | H13: 0 | I13: 0 | J13: 1 | K13: ✅
A14: =ROW()-2 -> 12 | B14: 2026-04-06 16:39:25 | C14: https://github.com/KaiPereira/Overglade-Badges | D14: safe | E14: Live Safe (Tech News) | F14: Aman | G14: 0 | H14: 0 | I14: 0 | J14: 1 | K14: ✅
... A1002: =ROW()-2 -> 1000 | B1002: 2026-05-11 13:08:50 | C1002: https://facebook-team.invoice-ads-manager.com/ | D1002: phishing | E1002: Typosquatting | F1002: Aman | G1002: 0 | H1002: 0 | I1002: 1 | J1002: 0 | K1002: ❌

Sheet Samsung Camera (Built-in)
A1: LOG PENGUJIAN: SAMSUNG CAMERA (BUILT-IN)
A2: No | B2: Waktu | C2: URL | D2: Label Aktual | E2: Kategori | F2: Hasil Scanner | G2: TP | H2: FP | I2: FN | J2: TN | K2: Benar? | L2: Catatan
A3: =ROW()-2 -> 1 | B3: 2026-04-07 18:01:42 | C3: https://www.science.org/content/blog-post/ah-peptides-where-begin | D3: safe | E3: Live Safe (Tech News) | F3: Aman | G3: 0 | H3: 0 | I3: 0 | J3: 1 | K3: ✅
A4: =ROW()-2 -> 2 | B4: 2026-04-07 18:01:55 | C4: https://krebsonsecurity.com/2026/04/germany-doxes-unkn-head-of-ru-ransomware-gangs-revil-gandcrab/ | D4: safe | E4: Live Safe (Tech News) | F4: Aman | G4: 0 | H4: 0 | I4: 0 | J4: 1 | K4: ✅
A5: =ROW()-2 -> 3 | B5: 2026-04-07 18:02:00 | C5: https://www.govauctions.app/ | D5: safe | E5: Live Safe (Tech News) | F5: Aman | G5: 0 | H5: 0 | I5: 0 | J5: 1 | K5: ✅
A6: =ROW()-2 -> 4 | B6: 2026-04-07 18:02:14 | C6: https://adashape.com | D6: safe | E6: Live Safe (Tech News) | F6: Aman | G6: 0 | H6: 0 | I6: 0 | J6: 1 | K6: ✅
A7: =ROW()-2 -> 5 | B7: 2026-04-07 18:02:24 | C7: https://belief.horse/notes/what-being-ripped-off-taught-me/ | D7: safe | E7: Live Safe (Tech News) | F7: Aman | G7: 0 | H7: 0 | I7: 0 | J7: 1 | K7: ✅
A8: =ROW()-2 -> 6 | B8: 2026-04-07 18:02:32 | C8: https://www.showbiz411.com/2026/04/05/itunes-takeover-by-fake-ai-singer-eddie-dalton-now-occupies-eleven-spots-on-chart-despite-not-being-human-or-real-exclusive | D8: safe | E8: Live Safe (Tech News) | F8: Aman | G8: 0 | H8: 0 | I8: 0 | J8: 1 | K8: ✅
A9: =ROW()-2 -> 7 | B9: 2026-04-07 18:02:40 | C9: https://www.stephendiehl.com/posts/no_antimimetics/ | D9: safe | E9: Live Safe (Tech News) | F9: Aman | G9: 0 | H9: 0 | I9: 0 | J9: 1 | K9: ✅
A10: =ROW()-2 -> 8 | B10: 2026-04-07 18:02:45 | C10: https://github.com/roscopeco/anos | D10: safe | E10: Live Safe (Tech News) | F10: Aman | G10: 0 | H10: 0 | I10: 0 | J10: 1 | K10: ✅
A11: =ROW()-2 -> 9 | B11: 2026-04-07 18:02:55 | C11: https://www.anthropic.com/news/google-broadcom-partnership-compute | D11: safe | E11: Live Safe (Tech News) | F11: Aman | G11: 0 | H11: 0 | I11: 0 | J11: 1 | K11: ✅
A12: =ROW()-2 -> 10 | B12: 2026-04-07 18:03:24 | C12: https://www.terrygodier.com/the-last-quiet-thing | D12: safe | E12: Live Safe (Tech News) | F12: Phishing | G12: 0 | H12: 1 | I12: 0 | J12: 0 | K12: ❌
A13: =ROW()-2 -> 11 | B13: 2026-04-07 18:03:29 | C13: https://github.com/Netflix/void-model | D13: safe | E13: Live Safe (Tech News) | F13: Aman | G13: 0 | H13: 0 | I13: 0 | J13: 1 | K13: ✅
A14: =ROW()-2 -> 12 | B14: 2026-04-07 18:03:34 | C14: https://github.com/kitfunso/hippo-memory | D14: safe | E14: Live Safe (Tech News) | F14: Aman | G14: 0 | H14: 0 | I14: 0 | J14: 1 | K14: ✅
... A190: =ROW()-2 -> 188 | B190: 2026-04-07 18:41:19 | C190: https://prtuge.com/ | D190: phishing | E190: Typosquatting | F190: Phishing | G190: 1 | H190: 0 | I190: 0 | J190: 0 | K190: ✅
A191: =ROW()-2 -> 189 | B191: 46119.362 | C191: https://trkloge23.serv00.net/dkb/login.php | D191: phishing | E191: Credential Harvesting | F191: Phishing | G191: 1 | H191: 0 | I191: 0 | J191: 0 | K191: ✅
A192: =ROW()-2 -> 190 | B192: 2026-04-07 08:40:54 | C192: https://trkloge23.serv00.net/dkb/login.php | D192: phishing | E192: Credential Harvesting | F192: Phishing | G192: 1 | H192: 0 | I192: 0 | J192: 0 | K192: ✅
A193: =ROW()-2 -> 191 | B193: 2026-04-07 08:41:04 | C193: https://trkloge23.serv00.net/dkb/login.php | D193: phishing | E193: Credential Harvesting | F193: Phishing | G193: 1 | H193: 0 | I193: 0 | J193: 0 | K193: ✅
A194: =ROW()-2 -> 192 | B194: 2026-04-07 17:45:30 | C194: https://ledger-com-start.vercel.app/ | D194: phishing | E194: Typosquatting | F194: Aman | G194: 0 | H194: 0 | I194: 1 | J194: 0 | K194: ❌
A195: =ROW()-2 -> 193 | B195: 2026-04-07 17:45:36 | C195: https://himani2484.github.io/amazon_clone/ | D195: phishing | E195: Typosquatting | F195: Aman | G195: 0 | H195: 0 | I195: 1 | J195: 0 | K195: ❌
A196: =ROW()-2 -> 194 | B196: 2026-04-07 17:45:51 | C196: https://invoicenotices.com/s/63BZGFSVBWSFCDX7Y9/584dd8/90eab167-7429-489f-99f6-ce86e8d0d81a | D196: phishing | E196: Typosquatting | F196: Aman | G196: 0 | H196: 0 | I196: 1 | J196: 0 | K196: ❌
A197: =ROW()-2 -> 195 | B197: 2026-04-07 17:45:58 | C197: https://135461223.site/sv/458/e44f214b-73f9-45e0-8ebb-2f43d17fd104/722221/x | D197: phishing | E197: Suspicious TLDs | F197: Aman | G197: 0 | H197: 0 | I197: 1 | J197: 0 | K197: ❌
A198: =ROW()-2 -> 196 | B198: 2026-04-07 17:46:07 | C198: https://roblox.com.ge/games/14751762996/JAGA-JAGA-ROBLOCKS-QUEEN?privateServerLinkCode=90159241212172745697009764022288 | D198: phishing | E198: Typosquatting | F198: Aman | G198: 0 | H198: 0 | I198: 1 | J198: 0 | K198: ❌
A199: =ROW()-2 -> 197 | B199: 2026-04-07 17:46:23 | C199: https://www.robiox.com.py/users/372564895763/profile | D199: phishing | E199: Typosquatting | F199: Aman | G199: 0 | H199: 0 | I199: 1 | J199: 0 | K199: ❌
A200: =ROW()-2 -> 198 | B200: 2026-04-07 17:46:32 | C200: https://hero-shanon.github.io/netflix-clone/ | D200: phishing | E200: Typosquatting | F200: Aman | G200: 0 | H200: 0 | I200: 1 | J200: 0 | K200: ❌
A201: =ROW()-2 -> 199 | B201: 2026-04-07 17:46:45 | C201: https://www.roblox.com.bn/games/131623223084840/Escape-Tsunami-For-Brainrots?privateServerLinkCode=80674271570847510930111301270272 | D201: phishing | E201: Typosquatting | F201: Aman | G201: 0 | H201: 0 | I201: 1 | J201: 0 | K201: ❌
A202: =ROW()-2 -> 200 | B202: 2026-04-07 17:46:55 | C202: https://roblox.com.ge/games/131378148336503/MODIF-x-EVENT-UPDATE-Drag-Drive-Simulator?privateServerLinkCode=14466708996407142075998321163891 | D202: phishing | E202: Credential Harvesting | F202: Aman | G202: 0 | H202: 0 | I202: 1 | J202: 0 | K202: ❌
A203: =ROW()-2 -> 201 | B203: 2026-04-07 18:01:42 | C203: https://www.science.org/content/blog-post/ah-peptides-where-begin | D203: safe | E203: Live Safe (Tech News) | F203: Aman | G203: 0 | H203: 0 | I203: 0 | J203: 1 | K203: ✅
... A1002: =ROW()-2 -> 1000 | B1002: 2026-05-11 17:51:06 | C1002: https://microsoft.authorised-support.com/new-account/EOzAFbYj1bjLmgufSIlKJJR9Kpvsy5kc3UkY=3Ag==3XlpQQVxAXFVHbF9cVFpdbERaR1tsQ1JAQERcQVc=/6Xx5KG1mKRNjeU3rSnC8diFTM7R4V1de | D1002: phishing | E1002: Credential Harvesting | F1002: Aman | G1002: 0 | H1002: 0 | I1002: 1 | J1002: 0 | K1002: ❌

Sheet Redmi Camera (Built-in)
A1: LOG PENGUJIAN: REDMI CAMERA (BUILT-IN)
A2: No | B2: Waktu | C2: URL | D2: Label Aktual | E2: Kategori | F2: Hasil Scanner | G2: TP | H2: FP | I2: FN | J2: TN | K2: Benar? | L2: Catatan
A3: =ROW()-2 -> 1 | B3: 2026-04-06 10:48:03 | C3: https://composerprogrammer.com/introductiontocomputermusic.pdf | D3: safe | E3: Live Safe (Tech News) | F3: Aman | G3: 0 | H3: 0 | I3: 0 | J3: 1 | K3: ✅
A4: =ROW()-2 -> 2 | B4: 2026-04-06 10:48:26 | C4: https://jaso1024.com/mvidia/ | D4: safe | E4: Live Safe (Tech News) | F4: Aman | G4: 0 | H4: 0 | I4: 0 | J4: 1 | K4: ✅
A5: =ROW()-2 -> 3 | B5: 2026-04-06 10:48:50 | C5: https://github.com/siddharthvaddem/openscreen | D5: safe | E5: Live Safe (Tech News) | F5: Aman | G5: 0 | H5: 0 | I5: 0 | J5: 1 | K5: ✅
A6: =ROW()-2 -> 4 | B6: 2026-04-06 10:49:04 | C6: https://taggart-tech.com/reckoning/ | D6: safe | E6: Live Safe (Tech News) | F6: Aman | G6: 0 | H6: 0 | I6: 0 | J6: 1 | K6: ✅
A7: =ROW()-2 -> 5 | B7: 2026-04-06 10:49:21 | C7: https://jonno.nz/posts/what-if-your-browser-built-the-ui-for-you/ | D7: safe | E7: Live Safe (Tech News) | F7: Aman | G7: 0 | H7: 0 | I7: 0 | J7: 1 | K7: ✅
A8: =ROW()-2 -> 6 | B8: 2026-04-06 10:49:39 | C8: https://gist.github.com/karpathy/442a6bf555914893e9891c11519de94f | D8: safe | E8: Live Safe (Tech News) | F8: Aman | G8: 0 | H8: 0 | I8: 0 | J8: 1 | K8: ✅
A9: =ROW()-2 -> 7 | B9: 2026-04-06 10:49:55 | C9: https://twitter.com/VladTheInflator/status/2039577001531768906 | D9: safe | E9: Live Safe (Tech News) | F9: Aman | G9: 0 | H9: 0 | I9: 0 | J9: 1 | K9: ✅
A10: =ROW()-2 -> 8 | B10: 2026-04-06 10:50:09 | C10: https://blog.djhaskin.com/blog/writing-lisp-is-ai-resistant-and-im-sad/ | D10: safe | E10: Live Safe (Tech News) | F10: Aman | G10: 0 | H10: 0 | I10: 0 | J10: 1 | K10: ✅
A11: =ROW()-2 -> 9 | B11: 2026-04-06 10:50:22 | C11: https://teybannerman.com/strategy/2026/03/31/how-many-microsoft-copilot-are-there.html | D11: safe | E11: Live Safe (Tech News) | F11: Aman | G11: 0 | H11: 0 | I11: 0 | J11: 1 | K11: ✅
A12: =ROW()-2 -> 10 | B12: 2026-04-06 10:50:35 | C12: https://www.phoronix.com/news/Linux-7.0-AWS-PostgreSQL-Drop | D12: safe | E12: Live Safe (Tech News) | F12: Aman | G12: 0 | H12: 0 | I12: 0 | J12: 1 | K12: ✅
A13: =ROW()-2 -> 11 | B13: 2026-04-06 10:50:50 | C13: https://www.science.org/doi/10.1126/sciadv.aef5697 | D13: safe | E13: Live Safe (Tech News) | F13: Aman | G13: 0 | H13: 0 | I13: 0 | J13: 1 | K13: ✅
A14: =ROW()-2 -> 12 | B14: 2026-04-06 10:51:04 | C14: https://github.com/KaiPereira/Overglade-Badges | D14: safe | E14: Live Safe (Tech News) | F14: Aman | G14: 0 | H14: 0 | I14: 0 | J14: 1 | K14: ✅
... A1002: =ROW()-2 -> 1000 | B1002: 2026-05-11 22:10:21 | C1002: https://microsoft.authorised-support.com/new-account/EOzAFbYj1bjLmgufSIlKJJR9Kpvsy5kc3UkY=3Ag==3XlpQQVxAXFVHbF9cVFpdbERaR1tsQ1JAQERcQVc=/6Xx5KG1mKRNjeU3rSnC8diFTM7R4V1de | D1002: phishing | E1002: Credential Harvesting | F1002: Phishing | G1002: 1 | H1002: 0 | I1002: 0 | J1002: 0 | K1002: ✅

Sheet Google Lens
A1: LOG PENGUJIAN: GOOGLE LENS
A2: No | B2: Waktu | C2: URL | D2: Label Aktual | E2: Kategori | F2: Hasil Scanner | G2: TP | H2: FP | I2: FN | J2: TN | K2: Benar? | L2: Catatan
A3: =ROW()-2 -> 1 | B3: 2026-04-07 07:59:57 | C3: https://composerprogrammer.com/introductiontocomputermusic.pdf | D3: safe | E3: Live Safe (Tech News) | F3: Aman | G3: 0 | H3: 0 | I3: 0 | J3: 1 | K3: ✅
A4: =ROW()-2 -> 2 | B4: 2026-04-07 08:00:15 | C4: https://jaso1024.com/mvidia/ | D4: safe | E4: Live Safe (Tech News) | F4: Aman | G4: 0 | H4: 0 | I4: 0 | J4: 1 | K4: ✅
A5: =ROW()-2 -> 3 | B5: 2026-04-07 08:00:39 | C5: https://github.com/siddharthvaddem/openscreen | D5: safe | E5: Live Safe (Tech News) | F5: Aman | G5: 0 | H5: 0 | I5: 0 | J5: 1 | K5: ✅
A6: =ROW()-2 -> 4 | B6: 2026-04-07 08:00:52 | C6: https://taggart-tech.com/reckoning/ | D6: safe | E6: Live Safe (Tech News) | F6: Aman | G6: 0 | H6: 0 | I6: 0 | J6: 1 | K6: ✅
A7: =ROW()-2 -> 5 | B7: 2026-04-07 08:01:01 | C7: https://jonno.nz/posts/what-if-your-browser-built-the-ui-for-you/ | D7: safe | E7: Live Safe (Tech News) | F7: Aman | G7: 0 | H7: 0 | I7: 0 | J7: 1 | K7: ✅
A8: =ROW()-2 -> 6 | B8: 2026-04-07 08:01:14 | C8: https://gist.github.com/karpathy/442a6bf555914893e9891c11519de94f | D8: safe | E8: Live Safe (Tech News) | F8: Aman | G8: 0 | H8: 0 | I8: 0 | J8: 1 | K8: ✅
A9: =ROW()-2 -> 7 | B9: 2026-04-07 08:01:37 | C9: https://twitter.com/VladTheInflator/status/2039577001531768906 | D9: safe | E9: Live Safe (Tech News) | F9: Aman | G9: 0 | H9: 0 | I9: 0 | J9: 1 | K9: ✅
A10: =ROW()-2 -> 8 | B10: 2026-04-07 08:01:45 | C10: https://blog.djhaskin.com/blog/writing-lisp-is-ai-resistant-and-im-sad/ | D10: safe | E10: Live Safe (Tech News) | F10: Aman | G10: 0 | H10: 0 | I10: 0 | J10: 1 | K10: ✅
A11: =ROW()-2 -> 9 | B11: 2026-04-07 08:01:52 | C11: https://teybannerman.com/strategy/2026/03/31/how-many-microsoft-copilot-are-there.html | D11: safe | E11: Live Safe (Tech News) | F11: Aman | G11: 0 | H11: 0 | I11: 0 | J11: 1 | K11: ✅
A12: =ROW()-2 -> 10 | B12: 2026-04-07 08:01:58 | C12: https://www.phoronix.com/news/Linux-7.0-AWS-PostgreSQL-Drop | D12: safe | E12: Live Safe (Tech News) | F12: Aman | G12: 0 | H12: 0 | I12: 0 | J12: 1 | K12: ✅
A13: =ROW()-2 -> 11 | B13: 2026-04-07 08:02:05 | C13: https://www.science.org/doi/10.1126/sciadv.aef5697 | D13: safe | E13: Live Safe (Tech News) | F13: Aman | G13: 0 | H13: 0 | I13: 0 | J13: 1 | K13: ✅
A14: =ROW()-2 -> 12 | B14: 2026-04-07 08:02:12 | C14: https://github.com/KaiPereira/Overglade-Badges | D14: safe | E14: Live Safe (Tech News) | F14: Aman | G14: 0 | H14: 0 | I14: 0 | J14: 1 | K14: ✅
... A40: =ROW()-2 -> 38 | B40: 2026-04-07 08:06:12 | C40: https://www.robiox.com.py/users/381961239698/profile | D40: phishing | E40: Typosquatting | F40: Aman | G40: 0 | H40: 0 | I40: 1 | J40: 0 | K40: ❌
A41: =ROW()-2 -> 39 | B41: 2026-04-07 08:10:18 | C41: http://p3bvt5dt5ra3gu.my.id/ | D41: phishing | E41: Mixed Content | F41: Phishing | G41: 1 | H41: 0 | I41: 0 | J41: 0 | K41: ✅ | L41: site can't be reached
A42: =ROW()-2 -> 40 | B42: 2026-04-07 08:10:38 | C42: https://trust-blockfi.webflow.io/ | D42: phishing | E42: Typosquatting | F42: Aman | G42: 0 | H42: 0 | I42: 1 | J42: 0 | K42: ❌
A43: =ROW()-2 -> 41 | B43: 2026-04-07 08:10:48 | C43: http://aktydnapyltr-idx.mmexe.my.id/ | D43: phishing | E43: Mixed Content | F43: Phishing | G43: 1 | H43: 0 | I43: 0 | J43: 0 | K43: ✅ | L43: site can't be reached
A44: =ROW()-2 -> 42 | B44: 2026-04-07 08:11:02 | C44: https://netflix-clone-mu-seven.vercel.app/ | D44: phishing | E44: Typosquatting | F44: Phishing | G44: 1 | H44: 0 | I44: 0 | J44: 0 | K44: ✅
A45: =ROW()-2 -> 43 | B45: 2026-04-07 08:11:18 | C45: http://www.netflix-clone-mu-seven.vercel.app/ | D45: phishing | E45: Mixed Content | F45: Phishing | G45: 1 | H45: 0 | I45: 0 | J45: 0 | K45: ✅
A46: =ROW()-2 -> 44 | B46: 2026-04-07 08:11:36 | C46: https://www.robiox.com.ps/games/920587237/Adopt-Me?privateServerLinkCode=41319586290522207122079569408427 | D46: phishing | E46: Typosquatting | F46: Phishing | G46: 1 | H46: 0 | I46: 0 | J46: 0 | K46: ✅ | L46: site can't be found
A47: =ROW()-2 -> 45 | B47: 2026-04-07 08:11:43 | C47: https://dpd.parcelroutepoint.cfd/com/ | D47: phishing | E47: Typosquatting | F47: Phishing | G47: 1 | H47: 0 | I47: 0 | J47: 0 | K47: ✅
A48: =ROW()-2 -> 46 | B48: 2026-04-07 08:11:48 | C48: https://dpd.parcelfollowhub.cfd/com/ | D48: phishing | E48: Typosquatting | F48: Phishing | G48: 1 | H48: 0 | I48: 0 | J48: 0 | K48: ✅
A49: =ROW()-2 -> 47 | B49: 2026-04-07 08:11:56 | C49: https://dpd.parcelroutenotice.cfd/com/ | D49: phishing | E49: Typosquatting | F49: Phishing | G49: 1 | H49: 0 | I49: 0 | J49: 0 | K49: ✅
A50: =ROW()-2 -> 48 | B50: 2026-04-07 08:11:59 | C50: https://dpd.parcelsignalpoint.cfd/com/ | D50: phishing | E50: Typosquatting | F50: Phishing | G50: 1 | H50: 0 | I50: 0 | J50: 0 | K50: ✅
A51: =ROW()-2 -> 49 | B51: 2026-04-07 08:12:03 | C51: http://bitfghurt-login.webflow.io/ | D51: phishing | E51: Mixed Content | F51: Phishing | G51: 1 | H51: 0 | I51: 0 | J51: 0 | K51: ✅
A52: =ROW()-2 -> 50 | B52: 2026-04-07 08:12:07 | C52: https://coinbase.aw-windblocker.com/ | D52: phishing | E52: Typosquatting | F52: Phishing | G52: 1 | H52: 0 | I52: 0 | J52: 0 | K52: ✅
A53: =ROW()-2 -> 51 | B53: 2026-04-07 08:12:11 | C53: https://coinbase.hrbwya.com/ | D53: phishing | E53: Typosquatting | F53: Phishing | G53: 1 | H53: 0 | I53: 0 | J53: 0 | K53: ✅
A54: =ROW()-2 -> 52 | B54: 2026-04-07 08:12:17 | C54: http://undian-whatsapp58.blogspot.com/ | D54: phishing | E54: Mixed Content | F54: Aman | G54: 0 | H54: 0 | I54: 1 | J54: 0 | K54: ❌
A55: =ROW()-2 -> 53 | B55: 2026-04-07 08:12:25 | C55: http://www.undian-whatsapp58.blogspot.com/ | D55: phishing | E55: Mixed Content | F55: Aman | G55: 0 | H55: 0 | I55: 1 | J55: 0 | K55: ❌
A56: =ROW()-2 -> 54 | B56: 2026-04-07 08:12:49 | C56: http://www.instagram-clone-sabitalizade.vercel.app/ | D56: phishing | E56: Mixed Content | F56: Phishing | G56: 1 | H56: 0 | I56: 0 | J56: 0 | K56: ✅ | L56: your connection is not private
A57: =ROW()-2 -> 55 | B57: 2026-04-07 08:13:03 | C57: http://www.mitrafreelancerjob.online/ | D57: phishing | E57: Suspicious TLDs | F57: Phishing | G57: 1 | H57: 0 | I57: 0 | J57: 0 | K57: ✅
A58: =ROW()-2 -> 56 | B58: 2026-04-07 08:13:07 | C58: https://dpd.parcelstakvl.bond/uk/ | D58: phishing | E58: Typosquatting | F58: Phishing | G58: 1 | H58: 0 | I58: 0 | J58: 0 | K58: ✅
A59: =ROW()-2 -> 57 | B59: 2026-04-07 08:13:11 | C59: https://dpd.parcelstakzu.bond/uk/ | D59: phishing | E59: Typosquatting | F59: Phishing | G59: 1 | H59: 0 | I59: 0 | J59: 0 | K59: ✅
A60: =ROW()-2 -> 58 | B60: 2026-04-07 08:13:15 | C60: https://dpd.parcelstakzy.bond/uk/ | D60: phishing | E60: Typosquatting | F60: Phishing | G60: 1 | H60: 0 | I60: 0 | J60: 0 | K60: ✅
A61: =ROW()-2 -> 59 | B61: 2026-04-07 08:13:20 | C61: https://dpd.parcelstakzp.bond/uk/ | D61: phishing | E61: Typosquatting | F61: Phishing | G61: 1 | H61: 0 | I61: 0 | J61: 0 | K61: ✅
A62: =ROW()-2 -> 60 | B62: 2026-04-07 08:13:23 | C62: https://dpd.tracess-pep.icu/com/ | D62: phishing | E62: Suspicious TLDs | F62: Phishing | G62: 1 | H62: 0 | I62: 0 | J62: 0 | K62: ✅
A63: =ROW()-2 -> 61 | B63: 2026-04-07 08:13:28 | C63: http://netflix-clone-alpha-nine.vercel.app/ | D63: phishing | E63: Mixed Content | F63: Phishing | G63: 1 | H63: 0 | I63: 0 | J63: 0 | K63: ✅
A64: =ROW()-2 -> 62 | B64: 2026-04-07 08:13:34 | C64: https://ntflx-reabonnieren.com/net/update.php | D64: phishing | E64: Credential Harvesting | F64: Phishing | G64: 1 | H64: 0 | I64: 0 | J64: 0 | K64: ✅
A65: =ROW()-2 -> 63 | B65: 2026-04-07 08:13:39 | C65: http://www.70774.xyz/ | D65: phishing | E65: Suspicious TLDs | F65: Phishing | G65: 1 | H65: 0 | I65: 0 | J65: 0 | K65: ✅
A66: =ROW()-2 -> 64 | B66: 2026-04-07 08:13:45 | C66: http://www.70769.xyz/ | D66: phishing | E66: Suspicious TLDs | F66: Phishing | G66: 1 | H66: 0 | I66: 0 | J66: 0 | K66: ✅
A67: =ROW()-2 -> 65 | B67: 2026-04-07 08:13:51 | C67: http://usmatamesk_log5.godaddysites.com/ | D67: phishing | E67: Mixed Content | F67: Aman | G67: 0 | H67: 0 | I67: 1 | J67: 0 | K67: ❌
A68: =ROW()-2 -> 66 | B68: 2026-04-07 08:13:59 | C68: http://sso-netcoins-ca-com--auth.webflow.io/ | D68: phishing | E68: Mixed Content | F68: Aman | G68: 0 | H68: 0 | I68: 1 | J68: 0 | K68: ❌
... A82: =ROW()-2 -> 80 | B82: 2026-04-07 08:15:35 | C82: https://www.robiox.com.py/users/134704267601/profile | D82: phishing | E82: Typosquatting | F82: Aman | G82: 0 | H82: 0 | I82: 1 | J82: 0 | K82: ❌
A83: =ROW()-2 -> 81 | B83: 2026-04-07 08:15:49 | C83: https://store.workshopvalvemods.com/sharedfiles/filesdetails/id=3368312736 | D83: phishing | E83: Typosquatting | F83: Phishing | G83: 1 | H83: 0 | I83: 0 | J83: 0 | K83: ✅ | L83: not found
A84: =ROW()-2 -> 82 | B84: 2026-04-07 08:15:56 | C84: https://bridge-begin.wixstudio.com/us-en | D84: phishing | E84: Typosquatting | F84: Aman | G84: 0 | H84: 0 | I84: 1 | J84: 0 | K84: ❌
A85: =ROW()-2 -> 83 | B85: 2026-04-07 08:16:02 | C85: https://visit-trezous.wixstudio.com/us-en | D85: phishing | E85: Typosquatting | F85: Aman | G85: 0 | H85: 0 | I85: 1 | J85: 0 | K85: ❌
A86: =ROW()-2 -> 84 | B86: 2026-04-07 08:17:16 | C86: https://visit-trezous.wixstudio.com/us-en | D86: phishing | E86: Typosquatting | F86: Phishing | G86: 1 | H86: 0 | I86: 0 | J86: 0 | K86: ✅ | L86: error: 404 page not found, tapi ada button untuk mengarahkan ke link baru (wix.com/studio)
A87: =ROW()-2 -> 85 | B87: 2026-04-07 08:17:29 | C87: https://platform-startio.wixstudio.com/en-us | D87: phishing | E87: Typosquatting | F87: Phishing | G87: 1 | H87: 0 | I87: 0 | J87: 0 | K87: ✅ | L87: sama seperti sebelumnya
A88: =ROW()-2 -> 86 | B88: 2026-04-07 08:17:35 | C88: https://alokkumar1212.github.io/Amazon-logo/ | D88: phishing | E88: Typosquatting | F88: Phishing | G88: 1 | H88: 0 | I88: 0 | J88: 0 | K88: ✅
A89: =ROW()-2 -> 87 | B89: 2026-04-07 08:17:39 | C89: https://kanxcode.github.io/stream-ui-demo/ | D89: phishing | E89: Typosquatting | F89: Phishing | G89: 1 | H89: 0 | I89: 0 | J89: 0 | K89: ✅
A90: =ROW()-2 -> 88 | B90: 2026-04-07 08:17:43 | C90: https://dpd.parcelstakvo.bond/com/ | D90: phishing | E90: Typosquatting | F90: Phishing | G90: 1 | H90: 0 | I90: 0 | J90: 0 | K90: ✅
A91: =ROW()-2 -> 89 | B91: 2026-04-07 08:17:46 | C91: https://dpd.parcelstahfz.bond/com/ | D91: phishing | E91: Typosquatting | F91: Phishing | G91: 1 | H91: 0 | I91: 0 | J91: 0 | K91: ✅
A92: =ROW()-2 -> 90 | B92: 2026-04-07 08:17:52 | C92: https://dpd.parcelstakug.bond/com/ | D92: phishing | E92: Typosquatting | F92: Phishing | G92: 1 | H92: 0 | I92: 0 | J92: 0 | K92: ✅
A93: =ROW()-2 -> 91 | B93: 2026-04-07 08:17:54 | C93: https://dpd.parcelstaklo.bond/com/ | D93: phishing | E93: Typosquatting | F93: Phishing | G93: 1 | H93: 0 | I93: 0 | J93: 0 | K93: ✅
A94: =ROW()-2 -> 92 | B94: 2026-04-07 08:17:58 | C94: https://dpd.parcelstaklr.bond/com/ | D94: phishing | E94: Typosquatting | F94: Phishing | G94: 1 | H94: 0 | I94: 0 | J94: 0 | K94: ✅
A95: =ROW()-2 -> 93 | B95: 2026-04-07 08:18:02 | C95: https://dpd.parcelstaklq.bond/com/ | D95: phishing | E95: Typosquatting | F95: Phishing | G95: 1 | H95: 0 | I95: 0 | J95: 0 | K95: ✅
A96: =ROW()-2 -> 94 | B96: 2026-04-07 08:18:06 | C96: https://dpd.parcelstaklx.bond/com/ | D96: phishing | E96: Typosquatting | F96: Phishing | G96: 1 | H96: 0 | I96: 0 | J96: 0 | K96: ✅
A97: =ROW()-2 -> 95 | B97: 2026-04-07 08:18:10 | C97: https://dpd.parcelstaklj.bond/com/ | D97: phishing | E97: Typosquatting | F97: Phishing | G97: 1 | H97: 0 | I97: 0 | J97: 0 | K97: ✅
A98: =ROW()-2 -> 96 | B98: 2026-04-07 08:18:15 | C98: https://dpd.parcelstakul.bond/com/ | D98: phishing | E98: Typosquatting | F98: Phishing | G98: 1 | H98: 0 | I98: 0 | J98: 0 | K98: ✅
A99: =ROW()-2 -> 97 | B99: 2026-04-07 08:18:20 | C99: https://dpd.parcelstakji.bond/com/ | D99: phishing | E99: Typosquatting | F99: Phishing | G99: 1 | H99: 0 | I99: 0 | J99: 0 | K99: ✅
... A123: =ROW()-2 -> 121 | B123: 2026-04-07 08:20:16 | C123: https://kunal-w07.github.io/netflix-clone/ | D123: phishing | E123: Typosquatting | F123: Phishing | G123: 1 | H123: 0 | I123: 0 | J123: 0 | K123: ✅
A124: =ROW()-2 -> 122 | B124: 2026-04-07 08:20:35 | C124: https://roblox.com.py/users/6662140597/profile | D124: phishing | E124: Typosquatting | F124: Phishing | G124: 1 | H124: 0 | I124: 0 | J124: 0 | K124: ✅ | L124: site can't be reached
A125: =ROW()-2 -> 123 | B125: 2026-04-07 08:20:44 | C125: https://en.securebanking.com.sg/s/63BZGFSVBWSFCDX7Y9/584dd8/90eab167-7429-489f-99f6-ce86e8d0d81a | D125: phishing | E125: Credential Harvesting | F125: Aman | G125: 0 | H125: 0 | I125: 1 | J125: 0 | K125: ❌
A126: =ROW()-2 -> 124 | B126: 2026-04-07 08:21:02 | C126: http://whatsappfcmobile.pages.dev/ | D126: phishing | E126: Mixed Content | F126: Aman | G126: 0 | H126: 0 | I126: 1 | J126: 0 | K126: ❌
A127: =ROW()-2 -> 125 | B127: 2026-04-07 08:21:07 | C127: https://livewallethelpdesk.com/ | D127: phishing | E127: Typosquatting | F127: Phishing | G127: 1 | H127: 0 | I127: 0 | J127: 0 | K127: ✅
A128: =ROW()-2 -> 126 | B128: 2026-04-07 08:23:23 | C128: https://roblox.gs/catalog?CatalogContext=1&Keyword= | D128: phishing | E128: Typosquatting | F128: Aman | G128: 0 | H128: 0 | I128: 1 | J128: 0 | K128: ❌
A129: =ROW()-2 -> 127 | B129: 2026-04-07 08:23:27 | C129: https://verifiedmeme.pages.dev/wallet/assets/unpkg.com/f..@1.5.3/dist/index-2.html | D129: phishing | E129: Mixed Content | F129: Phishing | G129: 1 | H129: 0 | I129: 0 | J129: 0 | K129: ✅
A130: =ROW()-2 -> 128 | B130: 2026-04-07 08:23:35 | C130: https://bridge-hub.wixstudio.com/en-us | D130: phishing | E130: Typosquatting | F130: Aman | G130: 0 | H130: 0 | I130: 1 | J130: 0 | K130: ❌
A131: =ROW()-2 -> 129 | B131: 2026-04-07 08:23:42 | C131: http://httpss-roblox.co/users/997900987/profile | D131: phishing | E131: Mixed Content | F131: Aman | G131: 0 | H131: 0 | I131: 1 | J131: 0 | K131: ❌
A132: =ROW()-2 -> 130 | B132: 2026-04-07 08:23:48 | C132: https://netflix-clone-azure-ten.vercel.app/ | D132: phishing | E132: Typosquatting | F132: Phishing | G132: 1 | H132: 0 | I132: 0 | J132: 0 | K132: ✅
A133: =ROW()-2 -> 131 | B133: 2026-04-07 08:24:00 | C133: https://www.robiox.com.py/users/301352583815/profile | D133: phishing | E133: Typosquatting | F133: Aman | G133: 0 | H133: 0 | I133: 1 | J133: 0 | K133: ❌
A134: =ROW()-2 -> 132 | B134: 2026-04-07 08:24:06 | C134: https://linkurl.pk/HXfeb-Ur | D134: phishing | E134: Typosquatting | F134: Phishing | G134: 1 | H134: 0 | I134: 0 | J134: 0 | K134: ✅
A135: =ROW()-2 -> 133 | B135: 2026-04-07 08:24:20 | C135: https://roblox.com.py/communities/7018013091/ | D135: phishing | E135: Typosquatting | F135: Phishing | G135: 1 | H135: 0 | I135: 0 | J135: 0 | K135: ✅ | L135: site can't be reached
A136: =ROW()-2 -> 134 | B136: 2026-04-07 08:25:06 | C136: http://www.is.gd/UfYiba/ | D136: phishing | E136: URL Shorteners | F136: Aman | G136: 0 | H136: 0 | I136: 1 | J136: 0 | K136: ❌ | L136: ada verification cloudflare dan aman.........
A137: =ROW()-2 -> 135 | B137: 2026-04-07 08:25:27 | C137: https://roblox.com.py/users/2159431803/profile | D137: phishing | E137: Typosquatting | F137: Phishing | G137: 1 | H137: 0 | I137: 0 | J137: 0 | K137: ✅ | L137: site can't be reached
A138: =ROW()-2 -> 136 | B138: 2026-04-07 08:25:50 | C138: https://365756zxd.com/index_m.html | D138: phishing | E138: Typosquatting | F138: Aman | G138: 0 | H138: 0 | I138: 1 | J138: 0 | K138: ❌
A139: =ROW()-2 -> 137 | B139: 2026-04-07 08:25:57 | C139: https://roblox.com.py/communities/6725198347/ | D139: phishing | E139: Typosquatting | F139: Phishing | G139: 1 | H139: 0 | I139: 0 | J139: 0 | K139: ✅ | L139: site can't be reached
A140: =ROW()-2 -> 138 | B140: 2026-04-07 08:26:05 | C140: https://instagram-home-page-clone.vercel.app/ | D140: phishing | E140: Typosquatting | F140: Phishing | G140: 1 | H140: 0 | I140: 0 | J140: 0 | K140: ✅
A141: =ROW()-2 -> 139 | B141: 2026-04-07 08:26:09 | C141: https://instalanding.vercel.app/ | D141: phishing | E141: Typosquatting | F141: Phishing | G141: 1 | H141: 0 | I141: 0 | J141: 0 | K141: ✅
A142: =ROW()-2 -> 140 | B142: 2026-04-07 08:26:12 | C142: https://vedavikasd.github.io/Amazon-Javascript-Project/ | D142: phishing | E142: Typosquatting | F142: Phishing | G142: 1 | H142: 0 | I142: 0 | J142: 0 | K142: ✅
A143: =ROW()-2 -> 141 | B143: 2026-04-07 08:26:16 | C143: https://rbxrewards.roblox-635.workers.dev/ | D143: phishing | E143: Typosquatting | F143: Phishing | G143: 1 | H143: 0 | I143: 0 | J143: 0 | K143: ✅
A144: =ROW()-2 -> 142 | B144: 2026-04-07 08:26:25 | C144: https://oei.028426.com/s/63BZGFSVBWSFCDX7Y9/584dd8/90eab167-7429-489f-99f6-ce86e8d0d81a | D144: phishing | E144: Typosquatting | F144: Aman | G144: 0 | H144: 0 | I144: 1 | J144: 0 | K144: ❌
A145: =ROW()-2 -> 143 | B145: 2026-04-07 08:26:29 | C145: http://gemini-logoin.godaddysites.com/ | D145: phishing | E145: Mixed Content | F145: Phishing | G145: 1 | H145: 0 | I145: 0 | J145: 0 | K145: ✅
A146: =ROW()-2 -> 144 | B146: 2026-04-07 08:26:34 | C146: https://lgiinkuconn.webflow.io/ | D146: phishing | E146: Typosquatting | F146: Phishing | G146: 1 | H146: 0 | I146: 0 | J146: 0 | K146: ✅
A147: =ROW()-2 -> 145 | B147: 2026-04-07 08:26:45 | C147: https://ipfs.io/ipfs/bafkreif73y3altm73krdreakpmyu73ehkkgv67exp2kssx6wjq7va7li5u?eta=3mail@a.b.c0 | D147: phishing | E147: Mixed Content | F147: Aman | G147: 0 | H147: 0 | I147: 1 | J147: 0 | K147: ❌
A148: =ROW()-2 -> 146 | B148: 2026-04-07 08:31:13 | C148: https://ademgucshop12pb.com/srbxzck/lzmgdrq/oqrgbka/tnde?uid=aaaa@example.jp | D148: phishing | E148: Mixed Content | F148: Phishing | G148: 1 | H148: 0 | I148: 0 | J148: 0 | K148: ✅ | L148: site can't be reached - loading take a long time
A149: =ROW()-2 -> 147 | B149: 2026-04-07 08:31:21 | C149: https://vd0511.github.io/Netflix-clone/ | D149: phishing | E149: Typosquatting | F149: Aman | G149: 0 | H149: 0 | I149: 1 | J149: 0 | K149: ❌
A150: =ROW()-2 -> 148 | B150: 2026-04-07 08:31:25 | C150: https://yuvarajsadam.github.io/netflix_clone/ | D150: phishing | E150: Typosquatting | F150: Phishing | G150: 1 | H150: 0 | I150: 0 | J150: 0 | K150: ✅
A151: =ROW()-2 -> 149 | B151: 2026-04-07 08:31:51 | C151: https://roblox.com.py/users/8081386220/profile | D151: phishing | E151: Typosquatting | F151: Phishing | G151: 1 | H151: 0 | I151: 0 | J151: 0 | K151: ✅
A152: =ROW()-2 -> 150 | B152: 2026-04-07 08:31:55 | C152: https://kmpnymrkziprmsynnktasi.info/754890001/ | D152: phishing | E152: Typosquatting | F152: Phishing | G152: 1 | H152: 0 | I152: 0 | J152: 0 | K152: ✅
A153: =ROW()-2 -> 151 | B153: 2026-04-07 08:32:03 | C153: https://135461223.site/no/465/26ec23ea-4d06-4ecb-afe7-5f50e82a46ad/719893/x | D153: phishing | E153: Suspicious TLDs | F153: Aman | G153: 0 | H153: 0 | I153: 1 | J153: 0 | K153: ❌
A154: =ROW()-2 -> 152 | B154: 2026-04-07 08:32:07 | C154: https://netflix-clone-coral-delta.vercel.app/ | D154: phishing | E154: Typosquatting | F154: Phishing | G154: 1 | H154: 0 | I154: 0 | J154: 0 | K154: ✅
A155: =ROW()-2 -> 153 | B155: 2026-04-07 08:32:12 | C155: https://netzero-mail-update-0f8eff.webflow.io/ | D155: phishing | E155: Credential Harvesting | F155: Phishing | G155: 1 | H155: 0 | I155: 0 | J155: 0 | K155: ✅
A156: =ROW()-2 -> 154 | B156: 2026-04-07 08:32:15 | C156: https://www.netflix-clone-coral-delta.vercel.app/ | D156: phishing | E156: Typosquatting | F156: Phishing | G156: 1 | H156: 0 | I156: 0 | J156: 0 | K156: ✅
A157: =ROW()-2 -> 155 | B157: 2026-04-07 08:32:23 | C157: https://nicholneelapu.github.io/Netflix_clone/ | D157: phishing | E157: Typosquatting | F157: Aman | G157: 0 | H157: 0 | I157: 1 | J157: 0 | K157: ❌
A158: =ROW()-2 -> 156 | B158: 2026-04-07 08:32:28 | C158: https://kaiser0207.github.io/HW3/ | D158: phishing | E158: Typosquatting | F158: Aman | G158: 0 | H158: 0 | I158: 1 | J158: 0 | K158: ❌
A159: =ROW()-2 -> 157 | B159: 2026-04-07 08:32:32 | C159: https://dpd.parcelvector.cfd/com | D159: phishing | E159: Typosquatting | F159: Phishing | G159: 1 | H159: 0 | I159: 0 | J159: 0 | K159: ✅
A160: =ROW()-2 -> 158 | B160: 2026-04-07 08:32:36 | C160: https://dpd.parceltranscore.cfd/com | D160: phishing | E160: Typosquatting | F160: Phishing | G160: 1 | H160: 0 | I160: 0 | J160: 0 | K160: ✅
... A183: =ROW()-2 -> 181 | B183: 2026-04-07 08:34:28 | C183: https://dpd.parcelcoreflow.cfd/com | D183: phishing | E183: Typosquatting | F183: Phishing | G183: 1 | H183: 0 | I183: 0 | J183: 0 | K183: ✅
...

Sheet Safe QR Code Reader
A1: LOG PENGUJIAN: Safe QR Code Reader
A2: No | B2: Waktu | C2: URL | D2: Label Aktual | E2: Kategori | F2: Hasil Scanner | G2: TP | H2: FP | I2: FN | J2: TN | K2: Benar? | L2: Catatan
A3: =ROW()-2 -> 1 | B3: 2026-04-07 17:04:57 | C3: https://composerprogrammer.com/introductiontocomputermusic.pdf | D3: safe | E3: Live Safe (Tech News) | F3: Phishing | G3: 0 | H3: 1 | I3: 0 | J3: 0 | K3: ❌
A4: =ROW()-2 -> 2 | B4: 2026-04-07 17:05:03 | C4: https://jaso1024.com/mvidia/ | D4: safe | E4: Live Safe (Tech News) | F4: Phishing | G4: 0 | H4: 1 | I4: 0 | J4: 0 | K4: ❌
A5: =ROW()-2 -> 3 | B5: 2026-04-07 17:05:11 | C5: https://github.com/siddharthvaddem/openscreen | D5: safe | E5: Live Safe (Tech News) | F5: Aman | G5: 0 | H5: 0 | I5: 0 | J5: 1 | K5: ✅
A6: =ROW()-2 -> 4 | B6: 2026-04-07 17:05:14 | C6: https://taggart-tech.com/reckoning/ | D6: safe | E6: Live Safe (Tech News) | F6: Aman | G6: 0 | H6: 0 | I6: 0 | J6: 1 | K6: ✅
A7: =ROW()-2 -> 5 | B7: 2026-04-07 17:05:55 | C7: https://jonno.nz/posts/what-if-your-browser-built-the-ui-for-you/ | D7: safe | E7: Live Safe (Tech News) | F7: Phishing | G7: 0 | H7: 1 | I7: 0 | J7: 0 | K7: ❌
A8: =ROW()-2 -> 6 | B8: 2026-04-07 17:06:00 | C8: https://gist.github.com/karpathy/442a6bf555914893e9891c11519de94f | D8: safe | E8: Live Safe (Tech News) | F8: Aman | G8: 0 | H8: 0 | I8: 0 | J8: 1 | K8: ✅
A9: =ROW()-2 -> 7 | B9: 2026-04-07 17:06:06 | C9: https://twitter.com/VladTheInflator/status/2039577001531768906 | D9: safe | E9: Live Safe (Tech News) | F9: Aman | G9: 0 | H9: 0 | I9: 0 | J9: 1 | K9: ✅
A10: =ROW()-2 -> 8 | B10: 2026-04-07 17:06:15 | C10: https://blog.djhaskin.com/blog/writing-lisp-is-ai-resistant-and-im-sad/ | D10: safe | E10: Live Safe (Tech News) | F10: Phishing | G10: 0 | H10: 1 | I10: 0 | J10: 0 | K10: ❌
A11: =ROW()-2 -> 9 | B11: 2026-04-07 17:06:19 | C11: https://teybannerman.com/strategy/2026/03/31/how-many-microsoft-copilot-are-there.html | D11: safe | E11: Live Safe (Tech News) | F11: Phishing | G11: 0 | H11: 1 | I11: 0 | J11: 0 | K11: ❌
A12: =ROW()-2 -> 10 | B12: 2026-04-07 17:06:24 | C12: https://www.phoronix.com/news/Linux-7.0-AWS-PostgreSQL-Drop | D12: safe | E12: Live Safe (Tech News) | F12: Aman | G12: 0 | H12: 0 | I12: 0 | J12: 1 | K12: ✅
A13: =ROW()-2 -> 11 | B13: 2026-04-07 17:06:28 | C13: https://www.science.org/doi/10.1126/sciadv.aef5697 | D13: safe | E13: Live Safe (Tech News) | F13: Aman | G13: 0 | H13: 0 | I13: 0 | J13: 1 | K13: ✅
A14: =ROW()-2 -> 12 | B14: 2026-04-07 17:06:32 | C14: https://github.com/KaiPereira/Overglade-Badges | D14: safe | E14: Live Safe (Tech News) | F14: Aman | G14: 0 | H14: 0 | I14: 0 | J14: 1 | K14: ✅
... A129: =ROW()-2 -> 127 | B129: 2026-04-07 17:15:32 | C129: https://bridge-hub.wixstudio.com/en-us | D129: phishing | E129: Typosquatting | F129: Phishing | G129: 1 | H129: 0 | I129: 0 | J129: 0 | K129: ✅
A130: =ROW()-2 -> 128 | B130: 2026-04-07 17:16:04 | C130: https://netflix-clone-azure-ten.vercel.app/ | D130: phishing | E130: Typosquatting | F130: Phishing | G130: 1 | H130: 0 | I130: 0 | J130: 0 | K130: ✅ | L130: unverified1
A131: =ROW()-2 -> 129 | B131: 2026-04-07 17:16:10 | C131: https://www.robiox.com.py/users/301352583815/profile | D131: phishing | E131: Typosquatting | F131: Phishing | G131: 1 | H131: 0 | I131: 0 | J131: 0 | K131: ✅ | L131: 1
A132: =ROW()-2 -> 130 | B132: 2026-04-07 17:16:13 | C132: https://linkurl.pk/HXfeb-Ur | D132: phishing | E132: Typosquatting | F132: Phishing | G132: 1 | H132: 0 | I132: 0 | J132: 0 | K132: ✅ | L132: 1
A133: =ROW()-2 -> 131 | B133: 2026-04-07 17:16:18 | C133: https://roblox.com.py/communities/7018013091/ | D133: phishing | E133: Typosquatting | F133: Phishing | G133: 1 | H133: 0 | I133: 0 | J133: 0 | K133: ✅ | L133: 1
A134: =ROW()-2 -> 132 | B134: 2026-04-07 17:16:24 | C134: http://www.is.gd/UfYiba/ | D134: phishing | E134: URL Shorteners | F134: Phishing | G134: 1 | H134: 0 | I134: 0 | J134: 0 | K134: ✅ | L134: 1
A135: =ROW()-2 -> 133 | B135: 2026-04-07 17:16:28 | C135: https://roblox.com.py/users/2159431803/profile | D135: phishing | E135: Typosquatting | F135: Phishing | G135: 1 | H135: 0 | I135: 0 | J135: 0 | K135: ✅ | L135: 1
A136: =ROW()-2 -> 134 | B136: 2026-04-07 17:16:32 | C136: https://365756zxd.com/index_m.html | D136: phishing | E136: Typosquatting | F136: Phishing | G136: 1 | H136: 0 | I136: 0 | J136: 0 | K136: ✅ | L136: 1
A137: =ROW()-2 -> 135 | B137: 2026-04-07 17:17:05 | C137: https://roblox.com.py/communities/6725198347/ | D137: phishing | E137: Typosquatting | F137: Aman | G137: 0 | H137: 0 | I137: 1 | J137: 0 | K137: ❌ | L137: 2
A138: =ROW()-2 -> 136 | B138: 2026-04-07 17:17:10 | C138: https://instagram-home-page-clone.vercel.app/ | D138: phishing | E138: Typosquatting | F138: Phishing | G138: 1 | H138: 0 | I138: 0 | J138: 0 | K138: ✅ | L138: 1
A139: =ROW()-2 -> 137 | B139: 2026-04-07 17:17:16 | C139: https://instalanding.vercel.app/ | D139: phishing | E139: Typosquatting | F139: Phishing | G139: 1 | H139: 0 | I139: 0 | J139: 0 | K139: ✅ | L139: 1
A140: =ROW()-2 -> 138 | B140: 2026-04-07 17:17:20 | C140: https://vedavikasd.github.io/Amazon-Javascript-Project/ | D140: phishing | E140: Typosquatting | F140: Phishing | G140: 1 | H140: 0 | I140: 0 | J140: 0 | K140: ✅ | L140: 1
A141: =ROW()-2 -> 139 | B141: 2026-04-07 17:17:24 | C141: https://rbxrewards.roblox-635.workers.dev/ | D141: phishing | E141: Typosquatting | F141: Phishing | G141: 1 | H141: 0 | I141: 0 | J141: 0 | K141: ✅ | L141: 1
... A152: =ROW()-2 -> 150 | B152: 2026-04-07 17:20:48 | C152: https://netflix-clone-coral-delta.vercel.app/ | D152: phishing | E152: Typosquatting | F152: Phishing | G152: 1 | H152: 0 | I152: 0 | J152: 0 | K152: ✅ | L152: 1
A153: =ROW()-2 -> 151 | B153: 2026-04-07 17:20:54 | C153: https://netflix-clone-coral-delta.vercel.app/ | D153: phishing | E153: Typosquatting | F153: Phishing | G153: 1 | H153: 0 | I153: 0 | J153: 0 | K153: ✅
A154: =ROW()-2 -> 152 | B154: 2026-04-07 17:21:00 | C154: https://netflix-clone-coral-delta.vercel.app/ | D154: phishing | E154: Typosquatting | F154: Phishing | G154: 1 | H154: 0 | I154: 0 | J154: 0 | K154: ✅ | L154: 1
A155: =ROW()-2 -> 153 | B155: 2026-04-07 17:21:19 | C155: https://netzero-mail-update-0f8eff.webflow.io/ | D155: phishing | E155: Credential Harvesting | F155: Phishing | G155: 1 | H155: 0 | I155: 0 | J155: 0 | K155: ✅ | L155: 1
A156: =ROW()-2 -> 154 | B156: 2026-04-07 17:21:24 | C156: https://www.netflix-clone-coral-delta.vercel.app/ | D156: phishing | E156: Typosquatting | F156: Phishing | G156: 1 | H156: 0 | I156: 0 | J156: 0 | K156: ✅ | L156: 1
A157: =ROW()-2 -> 155 | B157: 2026-04-07 17:21:28 | C157: https://nicholneelapu.github.io/Netflix_clone/ | D157: phishing | E157: Typosquatting | F157: Phishing | G157: 1 | H157: 0 | I157: 0 | J157: 0 | K157: ✅ | L157: 1
A158: =ROW()-2 -> 156 | B158: 2026-04-07 17:21:34 | C158: https://kaiser0207.github.io/HW3/ | D158: phishing | E158: Typosquatting | F158: Phishing | G158: 1 | H158: 0 | I158: 0 | J158: 0 | K158: ✅ | L158: 1
A159: =ROW()-2 -> 157 | B159: 2026-04-07 17:21:39 | C159: https://dpd.parcelvector.cfd/com | D159: phishing | E159: Typosquatting | F159: Phishing | G159: 1 | H159: 0 | I159: 0 | J159: 0 | K159: ✅ | L159: 1
A160: =ROW()-2 -> 158 | B160: 2026-04-07 17:21:41 | C160: https://dpd.parceltranscore.cfd/com | D160: phishing | E160: Typosquatting | F160: Phishing | G160: 1 | H160: 0 | I160: 0 | J160: 0 | K160: ✅ | L160: 1
A161: =ROW()-2 -> 159 | B161: 2026-04-07 17:21:44 | C161: https://dpd.parcelservicecenter.cfd/com | D161: phishing | E161: Typosquatting | F161: Phishing | G161: 1 | H161: 0 | I161: 0 | J161: 0 | K161: ✅ | L161: 1
A162: =ROW()-2 -> 160 | B162: 2026-04-07 17:21:48 | C162: https://jexi-bank.vercel.app/ | D162: phishing | E162: Typosquatting | F162: Phishing | G162: 1 | H162: 0 | I162: 0 | J162: 0 | K162: ✅ | L162: 1
A163: =ROW()-2 -> 161 | B163: 2026-04-07 17:21:51 | C163: https://swarna3108.github.io/project-3/ | D163: phishing | E163: Typosquatting | F163: Phishing | G163: 1 | H163: 0 | I163: 0 | J163: 0 | K163: ✅ | L163: 1
A164: =ROW()-2 -> 162 | B164: 2026-04-07 17:21:54 | C164: https://dpd.parcelserviceupdate.cfd/com | D164: phishing | E164: Credential Harvesting | F164: Phishing | G164: 1 | H164: 0 | I164: 0 | J164: 0 | K164: ✅ | L164: 1
A165: =ROW()-2 -> 163 | B165: 2026-04-07 17:21:57 | C165: https://dpd.parcelsignaldesk.cfd/com | D165: phishing | E165: Typosquatting | F165: Phishing | G165: 1 | H165: 0 | I165: 0 | J165: 0 | K165: ✅ | L165: 1
... A402: =ROW()-2 -> 400 | B402: 2026-04-07 19:11:54 | C402: http://www.mkj.linkpc.net/ | D402: phishing | E402: Mixed Content | F402: Phishing | G402: 1 | H402: 0 | I402: 0 | J402: 0 | K402: ✅ | L402: 1
A403: =ROW()-2 -> 401 | B403: 2026-05-11 14:38:32 | C403: https://www.digitalfoundry.net/news/2026/05/valve-releases-steam-controller-cad-files-under-creative-commons-license | D403: safe | E403: Live Safe (Tech News) | F403: Aman | G403: 0 | H403: 0 | I403: 0 | J403: 1 | K403: ✅
A404: =ROW()-2 -> 402 | B404: 2026-05-11 14:38:45 | C404: https://nooneshappy.com/article/appearing-productive-in-the-workplace/ | D404: safe | E404: Live Safe (Tech News) | F404: Phishing | G404: 0 | H404: 1 | I404: 0 | J404: 0 | K404: ❌
A405: =ROW()-2 -> 403 | B405: 2026-05-11 14:38:51 | C405: https://permacomputing.net/principles/ | D405: safe | E405: Live Safe (Tech News) | F405: Phishing | G405: 0 | H405: 1 | I405: 0 | J405: 0 | K405: ❌
A406: =ROW()-2 -> 404 | B406: 2026-05-11 14:38:59 | C406: https://aniket.foo/posts/20260505-netboot/ | D406: safe | E406: Live Safe (Tech News) | F406: Phishing | G406: 0 | H406: 1 | I406: 0 | J406: 0 | K406: ❌
A407: =ROW()-2 -> 405 | B407: 2026-05-11 14:39:04 | C407: https://sqlite.org/locrsf.html | D407: safe | E407: Live Safe (Tech News) | F407: Aman | G407: 0 | H407: 0 | I407: 0 | J407: 1 | K407: ✅
A408: =ROW()-2 -> 406 | B408: 2026-05-11 14:39:08 | C408: https://simonwillison.net/2026/May/6/vibe-coding-and-agentic-engineering/ | D408: safe | E408: Live Safe (Tech News) | F408: Phishing | G408: 0 | H408: 1 | I408: 0 | J408: 0 | K408: ❌
A409: =ROW()-2 -> 407 | B409: 2026-05-11 14:39:13 | C409: https://www.chevrolet.com/performance-parts/crate-engines/ecrate | D409: safe | E409: Live Safe (Tech News) | F409: Aman | G409: 0 | H409: 0 | I409: 0 | J409: 1 | K409: ✅
A410: =ROW()-2 -> 408 | B410: 2026-05-11 14:39:18 | C410: https://arxiv.org/abs/2605.03546 | D410: safe | E410: Live Safe (Tech News) | F410: Aman | G410: 0 | H410: 0 | I410: 0 | J410: 1 | K410: ✅
A411: =ROW()-2 -> 409 | B411: 2026-05-11 14:39:23 | C411: https://github.com/darkrishabh/agent-skills-eval | D411: safe | E411: Live Safe (Tech News) | F411: Aman | G411: 0 | H411: 0 | I411: 0 | J411: 1 | K411: ✅
A412: =ROW()-2 -> 410 | B412: 2026-05-11 14:39:27 | C412: https://shkspr.mobi/blog/2026/05/rss-feeds-send-me-more-traffic-than-google/ | D412: safe | E412: Live Safe (Tech News) | F412: Aman | G412: 0 | H412: 0 | I412: 0 | J412: 1 | K412: ✅
A413: =ROW()-2 -> 411 | B413: 2026-05-11 14:39:33 | C413: https://www.quantamagazine.org/the-hidden-mathematical-dance-inside-plant-cells-20260504/ | D413: safe | E413: Live Safe (Tech News) | F413: Aman | G413: 0 | H413: 0 | I413: 0 | J413: 1 | K413: ✅
A414: =ROW()-2 -> 412 | B414: 2026-05-11 14:39:37 | C414: https://blog.val.town/better-auth | D414: safe | E414: Live Safe (Tech News) | F414: Phishing | G414: 0 | H414: 1 | I414: 0 | J414: 0 | K414: ❌
... A902: =ROW()-2 -> 900 | B902: 2026-05-11 22:23:18 | C902: https://bafybeibkvhbsc2o2zbzilygrls65uyxmbxfdnk3mz35buvooyah7jpsbua.ipfs.dweb.link/ | D902: phishing | E902: Typosquatting | F902: Phishing | G902: 1 | H902: 0 | I902: 0 | J902: 0 | K902: ✅
A903: =ROW()-2 -> 901 | B903: 2026-04-08 03:40:19 | C903: https://ccunpacked.dev/ | D903: safe | E903: Live Safe (Tech News) | F903: Phishing | G903: 0 | H903: 1 | I903: 0 | J903: 0 | K903: ❌ | L903: unverified
A904: =ROW()-2 -> 902 | B904: 2026-04-08 03:40:26 | C904: https://home.cern/news/news/engineering/cern-levels-new-superconducting-karts | D904: safe | E904: Live Safe (Tech News) | F904: Aman | G904: 0 | H904: 0 | I904: 0 | J904: 1 | K904: ✅
A905: =ROW()-2 -> 903 | B905: 2026-04-08 03:40:31 | C905: https://www.science.org/content/article/neanderthals-survived-knife-s-edge-350-000-years | D905: safe | E905: Live Safe (Tech News) | F905: Aman | G905: 0 | H905: 0 | I905: 0 | J905: 1 | K905: ✅
A906: =ROW()-2 -> 904 | B906: 2026-04-08 03:40:38 | C906: https://blog.calif.io/p/mad-bugs-vim-vs-emacs-vs-claude | D906: safe | E906: Live Safe (Tech News) | F906: Phishing | G906: 0 | H906: 1 | I906: 0 | J906: 0 | K906: ❌ | L906: unverified
A907: =ROW()-2 -> 905 | B907: 2026-04-08 03:40:44 | C907: https://www.jeffgeerling.com/blog/2026/minidv-with-raspberry-pi-firewire-hat/ | D907: safe | E907: Live Safe (Tech News) | F907: Aman | G907: 0 | H907: 0 | I907: 0 | J907: 1 | K907: ✅
A908: =ROW()-2 -> 906 | B908: 2026-04-08 03:40:49 | C908: https://arxiv.org/abs/2602.04118 | D908: safe | E908: Live Safe (Tech News) | F908: Aman | G908: 0 | H908: 0 | I908: 0 | J908: 1 | K908: ✅
A909: =ROW()-2 -> 907 | B909: 2026-04-08 03:40:58 | C909: https://chrisseaton.com/truffleruby/ | D909: safe | E909: Live Safe (Tech News) | F909: Phishing | G909: 0 | H909: 1 | I909: 0 | J909: 0 | K909: ❌ | L909: unverified
A910: =ROW()-2 -> 908 | B910: 2026-04-08 03:41:06 | C910: https://prismml.com/ | D910: safe | E910: Live Safe (Tech News) | F910: Phishing | G910: 0 | H910: 1 | I910: 0 | J910: 0 | K910: ❌ | L910: unverified
A911: =ROW()-2 -> 909 | B911: 2026-04-08 03:41:14 | C911: https://scottlawsonbc.com/post/dot-system | D911: safe | E911: Live Safe (Tech News) | F911: Phishing | G911: 0 | H911: 1 | I911: 0 | J911: 0 | K911: ❌ | L911: unverified
A912: =ROW()-2 -> 910 | B912: 2026-04-08 03:41:21 | C912: https://github.com/yannick-cw/korb | D912: safe | E912: Live Safe (Tech News) | F912: Aman | G912: 0 | H912: 0 | I912: 0 | J912: 1 | K912: ✅
A913: =ROW()-2 -> 911 | B913: 2026-04-08 03:41:30 | C913: https://ministack.org/ | D913: safe | E913: Live Safe (Tech News) | F913: Phishing | G913: 0 | H913: 1 | I913: 0 | J913: 0 | K913: ❌ | L913: unverified
A914: =ROW()-2 -> 912 | B914: 2026-04-08 03:41:36 | C914: https://alex000kim.com/posts/2026-03-31-claude-code-source-leak/ | D914: safe | E914: Live Safe (Tech News) | F914: Phishing | G914: 0 | H914: 1 | I914: 0 | J914: 0 | K914: ❌ | L914: unverified
A915: =ROW()-2 -> 913 | B915: 2026-04-08 03:41:44 | C915: https://www.dbpro.app/blog/chess-in-pure-sql | D915: safe | E915: Live Safe (Tech News) | F915: Phishing | G915: 0 | H915: 1 | I915: 0 | J915: 0 | K915: ❌ | L915: unverified
A916: =ROW()-2 -> 914 | B916: 2026-04-08 03:41:49 | C916: https://www.cnbc.com/2026/03/31/openai-funding-round-ipo.html | D916: safe | E916: Live Safe (Tech News) | F916: Aman | G916: 0 | H916: 0 | I916: 0 | J916: 1 | K916: ✅
A917: =ROW()-2 -> 915 | B917: 2026-04-08 03:41:56 | C917: https://swiftrocks.com/digitizing-photos-from-the-1998-game-boy-camera | D917: safe | E917: Live Safe (Tech News) | F917: Phishing | G917: 0 | H917: 1 | I917: 0 | J917: 0 | K917: ❌ | L917: unverified
A918: =ROW()-2 -> 916 | B918: 2026-04-08 03:42:02 | C918: http://lughat.blogspot.com/2017/10/butterfly-collecting-history-of-insult.html | D918: safe | E918: Live Safe (Tech News) | F918: Aman | G918: 0 | H918: 0 | I918: 0 | J918: 1 | K918: ✅
A919: =ROW()-2 -> 917 | B919: 2026-04-08 03:42:06 | C919: https://www.geekbench.com/blog/2026/03/analyzing-geekbench-6-under-intels-bot/ | D919: safe | E919: Live Safe (Tech News) | F919: Aman | G919: 0 | H919: 0 | I919: 0 | J919: 1 | K919: ✅
A920: =ROW()-2 -> 918 | B920: 2026-04-08 03:42:10 | C920: https://github.com/danieldugas/HYPERHELL | D920: safe | E920: Live Safe (Tech News) | F920: Aman | G920: 0 | H920: 0 | I920: 0 | J920: 1 | K920: ✅
A921: =ROW()-2 -> 919 | B921: 2026-04-08 03:42:16 | C921: https://www.greptile.com/blog/ai-slopware-future | D921: safe | E921: Live Safe (Tech News) | F921: Phishing | G921: 0 | H921: 1 | I921: 0 | J921: 0 | K921: ❌ | L921: unverified
A922: =ROW()-2 -> 920 | B922: 2026-04-08 03:42:22 | C922: https://nautil.us/ordinary-lab-gloves-may-have-skewed-microplastic-data-1279386 | D922: safe | E922: Live Safe (Tech News) | F922: Aman | G922: 0 | H922: 0 | I922: 0 | J922: 1 | K922: ✅
A923: =ROW()-2 -> 921 | B923: 2026-04-08 03:42:31 | C923: https://solvespace.com/webver.pl | D923: safe | E923: Live Safe (Tech News) | F923: Phishing | G923: 0 | H923: 1 | I923: 0 | J923: 0 | K923: ❌ | L923: unverified
A924: =ROW()-2 -> 922 | B924: 2026-04-08 03:42:38 | C924: https://responsiblestatecraft.org/iran-strait-of-hormuz/ | D924: safe | E924: Live Safe (Tech News) | F924: Phishing | G924: 0 | H924: 1 | I924: 0 | J924: 0 | K924: ❌ | L924: unverified
A925: =ROW()-2 -> 923 | B925: 2026-04-08 03:42:47 | C925: https://hypha.pub/back-to-freebsd-part-2 | D925: safe | E925: Live Safe (Tech News) | F925: Phishing | G925: 0 | H925: 1 | I925: 0 | J925: 0 | K925: ❌ | L925: unverified
A926: =ROW()-2 -> 924 | B926: 2026-04-08 03:42:52 | C926: https://github.com/ericlewis/libpo32 | D926: safe | E926: Live Safe (Tech News) | F926: Aman | G926: 0 | H926: 0 | I926: 0 | J926: 1 | K926: ✅
A927: =ROW()-2 -> 925 | B927: 2026-04-08 03:42:57 | C927: https://cohere.com/blog/transcribe | D927: safe | E927: Live Safe (Tech News) | F927: Aman | G927: 0 | H927: 0 | I927: 0 | J927: 1 | K927: ✅
A928: =ROW()-2 -> 926 | B928: 2026-04-08 03:43:03 | C928: https://www.stepsecurity.io/blog/axios-compromised-on-npm-malicious-versions-drop-remote-access-trojan | D928: safe | E928: Live Safe (Tech News) | F928: Phishing | G928: 0 | H928: 1 | I928: 0 | J928: 0 | K928: ❌ | L928: unverified
A929: =ROW()-2 -> 927 | B929: 2026-04-08 03:43:08 | C929: https://github.com/timescale/pg_textsearch | D929: safe | E929: Live Safe (Tech News) | F929: Aman | G929: 0 | H929: 0 | I929: 0 | J929: 1 | K929: ✅
A930: =ROW()-2 -> 928 | B930: 2026-04-08 03:43:16 | C930: https://tech.stonecharioteer.com/posts/2026/tailscale-exit-nodes/ | D930: safe | E930: Live Safe (Tech News) | F930: Phishing | G930: 0 | H930: 1 | I930: 0 | J930: 0 | K930: ❌ | L930: unverified
A931: =ROW()-2 -> 929 | B931: 2026-04-08 03:43:23 | C931: https://news.future-shock.ai/the-weight-of-remembering/ | D931: safe | E931: Live Safe (Tech News) | F931: Phishing | G931: 0 | H931: 1 | I931: 0 | J931: 0 | K931: ❌ | L931: unverified
A932: =ROW()-2 -> 930 | B932: 2026-04-08 03:43:28 | C932: https://www.os2museum.com/wp/learn-something-old-every-day-part-xviii-how-does-fpu-detection-work/ | D932: safe | E932: Live Safe (Tech News) | F932: Aman | G932: 0 | H932: 0 | I932: 0 | J932: 1 | K932: ✅
A933: =ROW()-2 -> 931 | B933: 2026-04-08 03:43:36 | C933: https://pedagiodigital-auto.com/atendimento/home.php | D933: phishing | E933: Typosquatting | F933: Phishing | G933: 1 | H933: 0 | I933: 0 | J933: 0 | K933: ✅
A934: =ROW()-2 -> 932 | B934: 2026-04-08 03:43:42 | C934: http://sso-en-ca-netcoins-com-nav-azure.webflow.io/ | D934: phishing | E934: Mixed Content | F934: Phishing | G934: 1 | H934: 0 | I934: 0 | J934: 0 | K934: ✅
A935: =ROW()-2 -> 933 | B935: 2026-04-08 03:43:46 | C935: https://ckoinsquayrelogin.webflow.io/ | D935: phishing | E935: Credential Harvesting | F935: Phishing | G935: 1 | H935: 0 | I935: 0 | J935: 0 | K935: ✅
A936: =ROW()-2 -> 934 | B936: 2026-04-08 03:43:50 | C936: http://www.instagram-clone-lime.vercel.app/ | D936: phishing | E936: Mixed Content | F936: Phishing | G936: 1 | H936: 0 | I936: 0 | J936: 0 | K936: ✅
A937: =ROW()-2 -> 935 | B937: 2026-04-08 03:43:53 | C937: https://kucologinn.webflow.io/ | D937: phishing | E937: Credential Harvesting | F937: Phishing | G937: 1 | H937: 0 | I937: 0 | J937: 0 | K937: ✅
A938: =ROW()-2 -> 936 | B938: 2026-04-08 03:43:56 | C938: http://www.netflix-clone-six-black.vercel.app/ | D938: phishing | E938: Mixed Content | F938: Phishing | G938: 1 | H938: 0 | I938: 0 | J938: 0 | K938: ✅
A939: =ROW()-2 -> 937 | B939: 2026-04-08 03:44:00 | C939: http://bafybeigbqwmxazxynaputje3qz5bp5im3grqzyqdzb3r3xb5uuzysijlt4.ipfs.infura-ipfs.io/ | D939: phishing | E939: Mixed Content | F939: Phishing | G939: 1 | H939: 0 | I939: 0 | J939: 0 | K939: ✅
A940: =ROW()-2 -> 938 | B940: 2026-04-08 03:44:03 | C940: http://bitmartloginx.webflow.io/ | D940: phishing | E940: Mixed Content | F940: Phishing | G940: 1 | H940: 0 | I940: 0 | J940: 0 | K940: ✅
A941: =ROW()-2 -> 939 | B941: 2026-04-08 03:44:06 | C941: https://kuocoinlognco.godaddysites.com/ | D941: phishing | E941: Typosquatting | F941: Phishing | G941: 1 | H941: 0 | I941: 0 | J941: 0 | K941: ✅
A942: =ROW()-2 -> 940 | B942: 2026-04-08 03:44:10 | C942: http://www.kuocoinlognco.godaddysites.com/ | D942: phishing | E942: Mixed Content | F942: Phishing | G942: 1 | H942: 0 | I942: 0 | J942: 0 | K942: ✅
A943: =ROW()-2 -> 941 | B943: 2026-04-08 03:44:13 | C943: https://shopeeid0277.blogspot.com/ | D943: phishing | E943: Typosquatting | F943: Phishing | G943: 1 | H943: 0 | I943: 0 | J943: 0 | K943: ✅
... A961: =ROW()-2 -> 959 | B961: 2026-04-08 03:46:23 | C961: http://hgbm.se/ | D961: phishing | E961: Mixed Content | F961: Phishing | G961: 1 | H961: 0 | I961: 0 | J961: 0 | K961: ✅
A962: =ROW()-2 -> 960 | B962: 2026-04-08 03:46:31 | C962: https://gb-hochbau.cc/Vergabe/Portal/BC92kLm/20260223/KFR-RFQ/Arbeiten-gemaess-Baubeschreibung/Anhange3 | D962: phishing | E962: Typosquatting | F962: Phishing | G962: 1 | H962: 0 | I962: 0 | J962: 0 | K962: ✅ | L962: unverified
A963: =ROW()-2 -> 961 | B963: 2026-04-08 03:46:36 | C963: http://www.robiox.com.py/users/217025834840/profile | D963: phishing | E963: Mixed Content | F963: Phishing | G963: 1 | H963: 0 | I963: 0 | J963: 0 | K963: ✅
A964: =ROW()-2 -> 962 | B964: 2026-04-08 03:46:39 | C964: https://changepasswordd.com/ | D964: phishing | E964: Typosquatting | F964: Phishing | G964: 1 | H964: 0 | I964: 0 | J964: 0 | K964: ✅
...

Sheet QR Scan Shield
A1: LOG PENGUJIAN: QR SCAN SHIELD
A2: No | B2: Waktu | C2: URL | D2: Label Aktual | E2: Kategori | F2: Hasil Scanner | G2: TP | H2: FP | I2: FN | J2: TN | K2: Benar? | L2: Catatan
A3: =ROW()-2 -> 1 | B3: 2026-04-06 16:54:55 | C3: https://composerprogrammer.com/introductiontocomputermusic.pdf | D3: safe | E3: Live Safe (Tech News) | F3: Aman | G3: 0 | H3: 0 | I3: 0 | J3: 1 | K3: ✅
A4: =ROW()-2 -> 2 | B4: 2026-04-06 16:54:56 | C4: https://jaso1024.com/mvidia/ | D4: safe | E4: Live Safe (Tech News) | F4: Aman | G4: 0 | H4: 0 | I4: 0 | J4: 1 | K4: ✅
A5: =ROW()-2 -> 3 | B5: 2026-04-06 16:54:56 | C5: https://github.com/siddharthvaddem/openscreen | D5: safe | E5: Live Safe (Tech News) | F5: Aman | G5: 0 | H5: 0 | I5: 0 | J5: 1 | K5: ✅
A6: =ROW()-2 -> 4 | B6: 2026-04-06 16:54:57 | C6: https://taggart-tech.com/reckoning/ | D6: safe | E6: Live Safe (Tech News) | F6: Aman | G6: 0 | H6: 0 | I6: 0 | J6: 1 | K6: ✅
A7: =ROW()-2 -> 5 | B7: 2026-04-06 16:54:57 | C7: https://jonno.nz/posts/what-if-your-browser-built-the-ui-for-you/ | D7: safe | E7: Live Safe (Tech News) | F7: Aman | G7: 0 | H7: 0 | I7: 0 | J7: 1 | K7: ✅
A8: =ROW()-2 -> 6 | B8: 2026-04-06 16:54:57 | C8: https://gist.github.com/karpathy/442a6bf555914893e9891c11519de94f | D8: safe | E8: Live Safe (Tech News) | F8: Aman | G8: 0 | H8: 0 | I8: 0 | J8: 1 | K8: ✅
A9: =ROW()-2 -> 7 | B9: 2026-04-06 16:54:57 | C9: https://twitter.com/VladTheInflator/status/2039577001531768906 | D9: safe | E9: Live Safe (Tech News) | F9: Aman | G9: 0 | H9: 0 | I9: 0 | J9: 1 | K9: ✅
A10: =ROW()-2 -> 8 | B10: 2026-04-06 16:54:57 | C10: https://blog.djhaskin.com/blog/writing-lisp-is-ai-resistant-and-im-sad/ | D10: safe | E10: Live Safe (Tech News) | F10: Aman | G10: 0 | H10: 0 | I10: 0 | J10: 1 | K10: ✅
A11: =ROW()-2 -> 9 | B11: 2026-04-06 16:54:57 | C11: https://teybannerman.com/strategy/2026/03/31/how-many-microsoft-copilot-are-there.html | D11: safe | E11: Live Safe (Tech News) | F11: Aman | G11: 0 | H11: 0 | I11: 0 | J11: 1 | K11: ✅
A12: =ROW()-2 -> 10 | B12: 2026-04-06 16:54:58 | C12: https://www.phoronix.com/news/Linux-7.0-AWS-PostgreSQL-Drop | D12: safe | E12: Live Safe (Tech News) | F12: Aman | G12: 0 | H12: 0 | I12: 0 | J12: 1 | K12: ✅
A13: =ROW()-2 -> 11 | B13: 2026-04-06 16:54:58 | C13: https://www.science.org/doi/10.1126/sciadv.aef5697 | D13: safe | E13: Live Safe (Tech News) | F13: Aman | G13: 0 | H13: 0 | I13: 0 | J13: 1 | K13: ✅
A14: =ROW()-2 -> 12 | B14: 2026-04-06 16:54:58 | C14: https://github.com/KaiPereira/Overglade-Badges | D14: safe | E14: Live Safe (Tech News) | F14: Aman | G14: 0 | H14: 0 | I14: 0 | J14: 1 | K14: ✅
... A1002: =ROW()-2 -> 1000 | B1002: 2026-05-11 12:59:53 | C1002: https://microsoft.authorised-support.com/new-account/EOzAFbYj1bjLmgufSIlKJJR9Kpvsy5kc3UkY=3Ag==3XlpQQVxAXFVHbF9cVFpdbERaR1tsQ1JAQERcQVc=/6Xx5KG1mKRNjeU3rSnC8diFTM7R4V1de | D1002: phishing | E1002: Credential Harvesting | F1002: Aman | G1002: 0 | H1002: 0 | I1002: 1 | J1002: 0 | K1002: ❌

Sheet Ringkasan
A1: RINGKASAN PERBANDINGAN SEMUA SCANNER
A2: Scanner | B2: TP | C2: FP | D2: FN | E2: TN | F2: Precision | G2: Recall | H2: F1-Score
A3: iOS Camera (Built-in) | B3: =IFERROR(SUMIF('iOS Camera (Built-in)'!D$3:D$989,"phishing",'iOS Camera (Built-in)'!G$3:G$989),0) -> 272 | C3: =IFERROR(SUMIF('iOS Camera (Built-in)'!D$3:D$989,"safe",'iOS Camera (Built-in)'!H$3:H$989),0) -> 3 | D3: =IFERROR(SUMIF('iOS Camera (Built-in)'!D$3:D$989,"phishing",'iOS Camera (Built-in)'!I$3:I$989),0) -> 566 | E3: =IFERROR(SUMIF('iOS Camera (Built-in)'!D$3:D$989,"safe",'iOS Camera (Built-in)'!J$3:J$989),0) -> 146 | F3: =IFERROR(B3/(B3+C3),0) -> 0.98909091 | G3: =IFERROR(B3/(B3+D3),0) -> 0.32458234 | H3: =IFERROR(2*F3*G3/(F3+G3),0) -> 0.48876909
A4: Samsung Camera (Built-in) | B4: =IFERROR(SUMIF('Samsung Camera (Built-in)'!D$3:D$999,"phishing",'Samsung Camera (Built-in)'!G$3:G$999),0) -> 344 | C4: =IFERROR(SUMIF('Samsung Camera (Built-in)'!D$3:D$999,"safe",'Samsung Camera (Built-in)'!H$3:H$999),0) -> 5 | D4: =IFERROR(SUMIF('Samsung Camera (Built-in)'!D$3:D$999,"phishing",'Samsung Camera (Built-in)'!I$3:I$999),0) -> 526 | E4: =IFERROR(SUMIF('Samsung Camera (Built-in)'!D$3:D$999,"safe",'Samsung Camera (Built-in)'!J$3:J$999),0) -> 122 | F4: =IFERROR(B4/(B4+C4),0) -> 0.98567335 | G4: =IFERROR(B4/(B4+D4),0) -> 0.3954023 | H4: =IFERROR(2*F4*G4/(F4+G4),0) -> 0.56439705
A5: Redmi Camera (Built-in) | B5: =IFERROR(SUMIF('Redmi Camera (Built-in)'!D$3:D$1000,"phishing",'Redmi Camera (Built-in)'!G$3:G$1000),0) -> 597 | C5: =IFERROR(SUMIF('Redmi Camera (Built-in)'!D$3:D$1000,"safe",'Redmi Camera (Built-in)'!H$3:H$1000),0) -> 4 | D5: =IFERROR(SUMIF('Redmi Camera (Built-in)'!D$3:D$1000,"phishing",'Redmi Camera (Built-in)'!I$3:I$1000),0) -> 252 | E5: =IFERROR(SUMIF('Redmi Camera (Built-in)'!D$3:D$1000,"safe",'Redmi Camera (Built-in)'!J$3:J$1000),0) -> 145 | F5: =IFERROR(B5/(B5+C5),0) -> 0.99334443 | G5: =IFERROR(B5/(B5+D5),0) -> 0.70318021 | H5: =IFERROR(2*F5*G5/(F5+G5),0) -> 0.82344828
A6: Google Lens | B6: =IFERROR(SUMIF('Google Lens'!D$3:D$994,"phishing",'Google Lens'!G$3:G$994),0) -> 607 | C6: =IFERROR(SUMIF('Google Lens'!D$3:D$994,"safe",'Google Lens'!H$3:H$994),0) -> 2 | D6: =IFERROR(SUMIF('Google Lens'!D$3:D$994,"phishing",'Google Lens'!I$3:I$994),0) -> 236 | E6: =IFERROR(SUMIF('Google Lens'!D$3:D$994,"safe",'Google Lens'!J$3:J$994),0) -> 147 | F6: =IFERROR(B6/(B6+C6),0) -> 0.99671593 | G6: =IFERROR(B6/(B6+D6),0) -> 0.72004745 | H6: =IFERROR(2*F6*G6/(F6+G6),0) -> 0.83608815
A7: Safe QR Code Reader | B7: =IFERROR(SUMIF('Safe QR Code Reader'!D$3:D$1000,"phishing",'Safe QR Code Reader'!G$3:G$1000),0) -> 753 | C7: =IFERROR(SUMIF('Safe QR Code Reader'!D$3:D$1000,"safe",'Safe QR Code Reader'!H$3:H$1000),0) -> 75 | D7: =IFERROR(SUMIF('Safe QR Code Reader'!D$3:D$1000,"phishing",'Safe QR Code Reader'!I$3:I$1000),0) -> 93 | E7: =IFERROR(SUMIF('Safe QR Code Reader'!D$3:D$1000,"safe",'Safe QR Code Reader'!J$3:J$1000),0) -> 77 | F7: =IFERROR(B7/(B7+C7),0) -> 0.90942029 | G7: =IFERROR(B7/(B7+D7),0) -> 0.89007092 | H7: =IFERROR(2*F7*G7/(F7+G7),0) -> 0.89964158
A8: QR Scan Shield | B8: =IFERROR(SUMIF('QR Scan Shield'!D$3:D$1000,"phishing",'QR Scan Shield'!G$3:G$1000),0) -> 0 | C8: =IFERROR(SUMIF('QR Scan Shield'!D$3:D$1000,"safe",'QR Scan Shield'!H$3:H$1000),0) -> 0 | D8: =IFERROR(SUMIF('QR Scan Shield'!D$3:D$1000,"phishing",'QR Scan Shield'!I$3:I$1000),0) -> 851 | E8: =IFERROR(SUMIF('QR Scan Shield'!D$3:D$1000,"safe",'QR Scan Shield'!J$3:J$1000),0) -> 147 | F8: =IFERROR(B8/(B8+C8),0) -> 0 | G8: =IFERROR(B8/(B8+D8),0) -> 0 | H8: =IFERROR(2*F8*G8/(F8+G8),0) -> 0
H11: n
